lio/__init__.py
lio/losses/__init__.py
lio/losses/classification.py
lio/losses/regression.py
lio/models/__init__.py
lio/models/layers.py
lio/models/mnist.py
lio/models/resnet.py
lio/observations/__init__.py
lio/observations/observers.py
lio/observations/samplers.py
lio/observations/transitions.py
lio/utils/__init__.py
lio/utils/metrics.py
lio/utils/data/__init__.py
lio/utils/data/dataset.py
lio/utils/data/load.py
lio/utils/data/sampler.py
lio/utils/plot/__init__.py
lio/utils/plot/data.py
lio/utils/plot/simplex.py
lio-0.3.0.dist-info/LICENSE
lio-0.3.0.dist-info/METADATA
lio-0.3.0.dist-info/WHEEL
lio-0.3.0.dist-info/top_level.txt
lio-0.3.0.dist-info/RECORD
